{"v":5,"entries":{"components-bottomtab--default":{"type":"story","id":"components-bottomtab--default","name":"Default","title":"Components/BottomTab","importPath":"./src/stories/components/BottomTab.stories.tsx","componentPath":"@/components/features","tags":["dev","test"]},"components-button--base":{"type":"story","id":"components-button--base","name":"Base","title":"Components/Button","importPath":"./src/stories/components/Button.stories.tsx","componentPath":"@/components/base","tags":["dev","test","autodocs"]},"components-button--outline":{"type":"story","id":"components-button--outline","name":"Outline","title":"Components/Button","importPath":"./src/stories/components/Button.stories.tsx","componentPath":"@/components/base","tags":["dev","test","autodocs"]},"components-button--disabled":{"type":"story","id":"components-button--disabled","name":"Disabled","title":"Components/Button","importPath":"./src/stories/components/Button.stories.tsx","componentPath":"@/components/base","tags":["dev","test","autodocs"]},"components-customcalendar--mobile-size":{"type":"story","id":"components-customcalendar--mobile-size","name":"Mobile Size","title":"Components/CustomCalendar","importPath":"./src/stories/components/CalendarMobile.stories.tsx","componentPath":"@/components/features/calendar","tags":["dev","test"]},"components-customcalendar--pc-size":{"type":"story","id":"components-customcalendar--pc-size","name":"PC Size","title":"Components/CustomCalendar","importPath":"./src/stories/components/CalendarPC.stories.tsx","componentPath":"@/components/features/calendar","tags":["dev","test"]},"components-checkbox--base":{"type":"story","id":"components-checkbox--base","name":"Base","title":"Components/CheckBox","importPath":"./src/stories/components/CheckBox.stories.tsx","tags":["dev","test"]},"components-datepicker--date-picker":{"type":"story","id":"components-datepicker--date-picker","name":"Date Picker","title":"Components/DatePicker","importPath":"./src/stories/components/DatePicker.stories.tsx","componentPath":"@/components/features","tags":["dev","test"]},"components-dialog--base":{"type":"story","id":"components-dialog--base","name":"Base","title":"Components/Dialog","importPath":"./src/stories/components/Dialog.stories.tsx","tags":["dev","test"]},"components-dialog--state-dialog":{"type":"story","id":"components-dialog--state-dialog","name":"State Dialog","title":"Components/Dialog","importPath":"./src/stories/components/DialogState.stories.tsx","tags":["dev","test"]},"components-dayeventlist--day-event-list":{"type":"story","id":"components-dayeventlist--day-event-list","name":"Day Event List","title":"Components/DayEventList","importPath":"./src/stories/components/EventBox.stories.tsx","componentPath":"@/components/features","tags":["dev","test","autodocs"]},"components-input--base":{"type":"story","id":"components-input--base","name":"Base","title":"Components/Input","importPath":"./src/stories/components/Input.stories.tsx","tags":["dev","test"]},"components-input--add-event-input":{"type":"story","id":"components-input--add-event-input","name":"Add Event Input","title":"Components/Input","importPath":"./src/stories/components/Input.stories.tsx","tags":["dev","test"]},"components-monthnavigator--month-navigator":{"type":"story","id":"components-monthnavigator--month-navigator","name":"Month Navigator","title":"Components/MonthNavigator","importPath":"./src/stories/components/MonthNavigator.stories.tsx","componentPath":"@/components/features","tags":["dev","test"]},"components-typography--base":{"type":"story","id":"components-typography--base","name":"Base","title":"Components/Typography","importPath":"./src/stories/components/Typography.stories.tsx","tags":["dev","test","autodocs"]},"components-typography--typewriter":{"type":"story","id":"components-typography--typewriter","name":"Typewriter","title":"Components/Typography","importPath":"./src/stories/components/Typography.stories.tsx","tags":["dev","test","autodocs"]},"pages-calendar--calendar":{"type":"story","id":"pages-calendar--calendar","name":"Calendar","title":"pages/Calendar","importPath":"./src/stories/pages/Calendar.stories.tsx","componentPath":"./src/components/layouts/CalendarPage.tsx","tags":["dev","test"]},"pages-feedpage--feed-page":{"type":"story","id":"pages-feedpage--feed-page","name":"Feed Page","title":"pages/FeedPage","importPath":"./src/stories/pages/Feed.stories.tsx","componentPath":"./src/components/layouts/FeedPage.tsx","tags":["dev","test"]},"pages-splash-screen--base":{"type":"story","id":"pages-splash-screen--base","name":"Base","title":"pages/splash-screen","importPath":"./src/stories/pages/splash-screen.stories.tsx","tags":["dev","test"]}}}